pybulma/__init__.py
pybulma/base.py
pybulma/basic.py
pybulma/breadcumb.py
pybulma/buttons.py
pybulma/card.py
pybulma/columns.py
pybulma/dropdown.py
pybulma/exceptions.py
pybulma/file_inputs.py
pybulma/form.py
pybulma/icon.py
pybulma/image.py
pybulma/jinja2.py
pybulma/layouts.py
pybulma/menu.py
pybulma/modals.py
pybulma/navbar.py
pybulma/page.py
pybulma/table.py
pybulma/tabs.py
pybulma/text.py
pybulma/static/__init__.py
pybulma/static/scripts/__init__.py
pybulma/static/scripts/brymodal.py
PyBulma-0.1.35.dist-info/LICENSE
PyBulma-0.1.35.dist-info/METADATA
PyBulma-0.1.35.dist-info/WHEEL
PyBulma-0.1.35.dist-info/top_level.txt
PyBulma-0.1.35.dist-info/RECORD
